Metadata-Version: 2.1
Name: ezzthread
Version: 1.0.0
Summary: Small decorator library for launching threads
Home-page: https://github.com/BarsTiger/thread
Author: BarsTiger
License: MIT
Keywords: threading,thread,decorator,crossplatform
Platform: UNKNOWN
License-File: LICENSE.txt
